zinnia_threaded_comments/__init__.py
zinnia_threaded_comments/admin.py
zinnia_threaded_comments/apps.py
zinnia_threaded_comments/forms.py
zinnia_threaded_comments/models.py
zinnia_threaded_comments/locale/fr/LC_MESSAGES/django.mo
zinnia_threaded_comments/locale/fr/LC_MESSAGES/django.po
zinnia_threaded_comments/migrations/0001_initial.py
zinnia_threaded_comments/migrations/0002_migrate_comments.py
zinnia_threaded_comments/migrations/__init__.py
zinnia_threaded_comments/static/zinnia_threaded_comments/config.rb
zinnia_threaded_comments/static/zinnia_threaded_comments/css/comment-reply.css
zinnia_threaded_comments/static/zinnia_threaded_comments/js/comment-reply.js
zinnia_threaded_comments/static/zinnia_threaded_comments/sass/comment-reply.scss
zinnia_threaded_comments/templates/comments/zinnia/entry/form.html
zinnia_threaded_comments/templates/zinnia/entry_detail_base.html
zinnia_threaded_comments-0.4.dist-info/DESCRIPTION.rst
zinnia_threaded_comments-0.4.dist-info/METADATA
zinnia_threaded_comments-0.4.dist-info/RECORD
zinnia_threaded_comments-0.4.dist-info/WHEEL
zinnia_threaded_comments-0.4.dist-info/metadata.json
zinnia_threaded_comments-0.4.dist-info/top_level.txt
