Metadata-Version: 2.0
Name: zinnia-threaded-comments
Version: 0.4
Summary: Threaded comments for django-blog-zinnia
Home-page: https://github.com/django-blog-zinnia/zinnia-threaded-comments
Author: Fantomas42
Author-email: fantomas42@gmail.com
License: BSD License
Keywords: django,blog,weblog,zinnia,comments,threaded
Platform: UNKNOWN
Classifier: Framework :: Django
Classifier: Development Status :: 5 - Production/Stable
Classifier: Environment :: Web Environment
Classifier: Programming Language :: Python
Classifier: Intended Audience :: Developers
Classifier: Operating System :: OS Independent
Classifier: License :: OSI Approved :: BSD License
Classifier: Topic :: Software Development :: Libraries :: Python Modules
